{
    "version": "0.4.22",
    "description": "vew -- a browser, with an agent built in.",
    "homepage": "https://vew.sh",
    "license": {
        "identifier": "Proprietary",
        "url": "https://vew.sh"
    },
    "architecture": {
        "64bit": {
            "url": "https://downloads.vew.sh/vew-win32-x64-0.4.22.zip",
            "hash": "73da28c9a37d15258d323c3cc6b7f0cd56faca82e7330cdd9b2c71e9aecc90a6"
        },
        "arm64": {
            "url": "https://downloads.vew.sh/vew-win32-arm64-0.4.22.zip",
            "hash": "07c6890517acc14754d680996edd0547187664e0fc9adafb0d3dd00056344203"
        }
    },
    "bin": [
        "vew.cmd"
    ],
    "shortcuts": [
        [
            "vew.exe",
            "vew"
        ]
    ],
    "pre_uninstall": [
        "if (Test-Path \"$dir\\vew.exe\") { Start-Process -FilePath \"$dir\\vew.exe\" -ArgumentList '--unregister-browser' -Wait }"
    ],
    "checkver": {
        "url": "https://vew.sh/version-windows.json",
        "jsonpath": "$.version"
    },
    "autoupdate": {
        "architecture": {
            "64bit": {
                "url": "https://downloads.vew.sh/vew-win32-x64-$version.zip"
            },
            "arm64": {
                "url": "https://downloads.vew.sh/vew-win32-arm64-$version.zip"
            }
        }
    }
}
